rancid_verifier/__init__.py
rancid_verifier/main.py
rancid_verifier/verification.py
rancid_verifier-0.2.0.dist-info/LICENSE
rancid_verifier-0.2.0.dist-info/METADATA
rancid_verifier-0.2.0.dist-info/WHEEL
rancid_verifier-0.2.0.dist-info/entry_points.txt
rancid_verifier-0.2.0.dist-info/RECORD
