Metadata-Version: 2.1
Name: rancid-verifier
Version: 0.2.0
Summary: Rancid verifier is a tool to check [rancid's](https://shrubbery.net/rancid) `router.db` file consistency. `router.db` format is described in [router.db(5)](https://shrubbery.net/rancid/man/router.db.5.html)
Author: Fedor Suchkov
Author-email: f.suchkov@gmail.com
Requires-Python: >=3.9,<4.0
Classifier: Programming Language :: Python :: 3
Classifier: Programming Language :: Python :: 3.9
Classifier: Programming Language :: Python :: 3.10
Classifier: Programming Language :: Python :: 3.11
Classifier: Programming Language :: Python :: 3.12
